testlibraryorsomething/__init__.py
testlibraryorsomething/test_functionality.py
testlibraryorsomething-1.0.3.dist-info/METADATA
testlibraryorsomething-1.0.3.dist-info/WHEEL
testlibraryorsomething-1.0.3.dist-info/top_level.txt
testlibraryorsomething-1.0.3.dist-info/RECORD
