Metadata-Version: 2.1
Name: testlibraryorsomething
Version: 1.0.3
Summary: Test Library or Something
Author: Bamboooz
Author-email: bambusixmc@gmail.com
